napari_tissuumaps/__init__.py
napari_tissuumaps/_version.py
napari_tissuumaps/_writer.py
napari_tissuumaps/convert.py
napari_tissuumaps/napari.yaml
napari_tissuumaps/_tests/__init__.py
napari_tissuumaps/_tests/test_writer.py
napari_tissuumaps/_tests/assets/labels.tif
napari_tissuumaps/_tests/assets/points.csv
napari_tissuumaps/_tests/assets/shapes.csv
napari_tissuumaps-1.1.2.dist-info/LICENSE
napari_tissuumaps-1.1.2.dist-info/METADATA
napari_tissuumaps-1.1.2.dist-info/WHEEL
napari_tissuumaps-1.1.2.dist-info/entry_points.txt
napari_tissuumaps-1.1.2.dist-info/top_level.txt
napari_tissuumaps-1.1.2.dist-info/RECORD
